[
  {
    "neighbourhood": "Achtse Barrier-Gunterslaer",
    "district": "Woensel-Noord",
    "2020": {
      "personal_income": 35700,
      "residents": 3721,
      "unhappy_percentage": 4,
      "prolonged_illness_percentage": 24,
      "high_level_of_education_percentage": 36.1
    }
  },
  {
    "neighbourhood": "Achtse Barrier-Hoeven",
    "district": "Woensel-Noord",
    "2020": {
      "personal_income": 34400,
      "residents": 3989,
      "unhappy_percentage": 5,
      "prolonged_illness_percentage": 25,
      "high_level_of_education_percentage": 31.7
    }
  },
  {
    "neighbourhood": "Achtse Barrier-Spaaihoef",
    "district": "Woensel-Noord",
    "2020": {
      "personal_income": 38600,
      "residents": 4505,
      "unhappy_percentage": 3,
      "prolonged_illness_percentage": 20,
      "high_level_of_education_percentage": 34.7
    }
  },
  {
    "neighbourhood": "Barrier",
    "district": "Woensel-Zuid",
    "2020": {
      "personal_income": 31600,
      "residents": 2130,
      "unhappy_percentage": 7,
      "prolonged_illness_percentage": 20,
      "high_level_of_education_percentage": 40.9
    }
  },
  {
    "neighbourhood": "Bennekel-Oost",
    "district": "Gestel",
    "2020": {
      "personal_income": 27800,
      "residents": 3402,
      "unhappy_percentage": 7,
      "prolonged_illness_percentage": 25,
      "high_level_of_education_percentage": 41.4
    }
  },
  {
    "neighbourhood": "Bennekel-West, Gagelbosch",
    "district": "Gestel",
    "2020": {
      "personal_income": 27600,
      "residents": 3388,
      "unhappy_percentage": 7,
      "prolonged_illness_percentage": 25,
      "high_level_of_education_percentage": 24.5
    }
  },
  {
    "neighbourhood": "Bergen",
    "district": "Centrum",
    "2020": {
      "personal_income": 42000,
      "residents": 2727,
      "unhappy_percentage": 6,
      "prolonged_illness_percentage": 15,
      "high_level_of_education_percentage": 58.7
    }
  },
  {
    "neighbourhood": "Binnenstad",
    "district": "Centrum",
    "2020": {
      "personal_income": 38500,
      "residents": 3750,
      "unhappy_percentage": 6,
      "prolonged_illness_percentage": 12,
      "high_level_of_education_percentage": 51.5
    }
  },
  {
    "neighbourhood": "Blaarthem",
    "district": "Gestel",
    "2020": {
      "personal_income": 28800,
      "residents": 2448,
      "unhappy_percentage": 7,
      "prolonged_illness_percentage": 25,
      "high_level_of_education_percentage": 28.4
    }
  },
  {
    "neighbourhood": "Blixembosch-Oost",
    "district": "Woensel-Noord",
    "2020": {
      "personal_income": 44100,
      "residents": 7246,
      "unhappy_percentage": 2,
      "prolonged_illness_percentage": 16,
      "high_level_of_education_percentage": 40.6
    }
  },
  {
    "neighbourhood": "Blixembosch-West",
    "district": "Woensel-Noord",
    "2020": {
      "personal_income": 45400,
      "residents": 2069,
      "unhappy_percentage": 2,
      "prolonged_illness_percentage": 16,
      "high_level_of_education_percentage": 0
    }
  },
  {
    "neighbourhood": "Bloemenplein",
    "district": "Stratum",
    "2020": {
      "personal_income": 32100,
      "residents": 1206,
      "unhappy_percentage": 8,
      "prolonged_illness_percentage": 18,
      "high_level_of_education_percentage": 30.7
    }
  },
  {
    "neighbourhood": "Bosrijk",
    "district": "Strijp",
    "2020": {
      "personal_income": 59700,
      "residents": 423,
      "unhappy_percentage": 2,
      "prolonged_illness_percentage": 14,
      "high_level_of_education_percentage": 62.5
    }
  },
  {
    "neighbourhood": "Burghplan",
    "district": "Stratum",
    "2020": {
      "personal_income": 30000,
      "residents": 3057,
      "unhappy_percentage": 8,
      "prolonged_illness_percentage": 25,
      "high_level_of_education_percentage": 28
    }
  },
  {
    "neighbourhood": "Doornakkers-Oost",
    "district": "Tongelre",
    "2020": {
      "personal_income": 25000,
      "residents": 2905,
      "unhappy_percentage": 8,
      "prolonged_illness_percentage": 22,
      "high_level_of_education_percentage": 19.9
    }
  },
  {
    "neighbourhood": "Doornakkers-West",
    "district": "Tongelre",
    "2020": {
      "personal_income": 28500,
      "residents": 3482,
      "unhappy_percentage": 8,
      "prolonged_illness_percentage": 22,
      "high_level_of_education_percentage": 32.7
    }
  },
  {
    "neighbourhood": "Drents Dorp",
    "district": "Strijp",
    "2020": {
      "personal_income": 27700,
      "residents": 2391,
      "unhappy_percentage": 3,
      "prolonged_illness_percentage": 16,
      "high_level_of_education_percentage": 23.9
    }
  },
  {
    "neighbourhood": "Driehoeksbos",
    "district": "Woensel-Noord",
    "2020": {
      "personal_income": 49800,
      "residents": 968,
      "unhappy_percentage": 8,
      "prolonged_illness_percentage": 24,
      "high_level_of_education_percentage": 43.1
    }
  },
  {
    "neighbourhood": "Eckart",
    "district": "Woensel-Noord",
    "2020": {
      "personal_income": 26300,
      "residents": 4302,
      "unhappy_percentage": 3,
      "prolonged_illness_percentage": 22,
      "high_level_of_education_percentage": 17.8
    }
  },
  {
    "neighbourhood": "Eikenburg",
    "district": "Stratum",
    "2020": {
      "personal_income": 51900,
      "residents": 4302,
      "unhappy_percentage": 3,
      "prolonged_illness_percentage": 14,
      "high_level_of_education_percentage": 49.6
    }
  },
  {
    "neighbourhood": "Eliasterrein, Vonderkwartier",
    "district": "Strijp",
    "2020": {
      "personal_income": 40100,
      "residents": 3166,
      "unhappy_percentage": 2,
      "prolonged_illness_percentage": 12,
      "high_level_of_education_percentage": 46.6
    }
  },
  {
    "neighbourhood": "Elzent-Noord",
    "district": "Stratum",
    "2020": {
      "personal_income": 54300,
      "residents": 1074,
      "unhappy_percentage": 1,
      "prolonged_illness_percentage": 15,
      "high_level_of_education_percentage": 42.2
    }
  },
  {
    "neighbourhood": "Elzent-Zuid",
    "district": "Stratum",
    "2020": {
      "personal_income": 65600,
      "residents": 301,
      "unhappy_percentage": 1,
      "prolonged_illness_percentage": 15,
      "high_level_of_education_percentage": 50
    }
  },
  {
    "neighbourhood": "Engelsbergen",
    "district": "Strijp",
    "2020": {
      "personal_income": 42500,
      "residents": 635,
      "unhappy_percentage": 2,
      "prolonged_illness_percentage": 12,
      "high_level_of_education_percentage": 59.6
    }
  },
  {
    "neighbourhood": "Genderbeemd",
    "district": "Gestel",
    "2020": {
      "personal_income": 35700,
      "residents": 3628,
      "unhappy_percentage": 4,
      "prolonged_illness_percentage": 29,
      "high_level_of_education_percentage": 41.5
    }
  },
  {
    "neighbourhood": "Genderdal",
    "district": "Gestel",
    "2020": {
      "personal_income": 26600,
      "residents": 2957,
      "unhappy_percentage": 9,
      "prolonged_illness_percentage": 28,
      "high_level_of_education_percentage": 34.8
    }
  },
  {
    "neighbourhood": "Generalenbuurt",
    "district": "Woensel-Zuid",
    "2020": {
      "personal_income": 30100,
      "residents": 5437,
      "unhappy_percentage": 4,
      "prolonged_illness_percentage": 27,
      "high_level_of_education_percentage": 30.3
    }
  },
  {
    "neighbourhood": "Genneperzijde",
    "district": "Stratum",
    "2020": {
      "personal_income": 43000,
      "residents": 1361,
      "unhappy_percentage": 1,
      "prolonged_illness_percentage": 15,
      "high_level_of_education_percentage": 53.7
    }
  },
  {
    "neighbourhood": "Gerardusplein",
    "district": "Stratum",
    "2020": {
      "personal_income": 38200,
      "residents": 3374,
      "unhappy_percentage": 4,
      "prolonged_illness_percentage": 16,
      "high_level_of_education_percentage": 43.1
    }
  },
  {
    "neighbourhood": "Gijzenrooi",
    "district": "Stratum",
    "2020": {
      "personal_income": 47700,
      "residents": 1818,
      "unhappy_percentage": 2,
      "prolonged_illness_percentage": 16,
      "high_level_of_education_percentage": 52.4
    }
  },
  {
    "neighbourhood": "Gildebuurt",
    "district": "Woensel-Zuid",
    "2020": {
      "personal_income": 30300,
      "residents": 1681,
      "unhappy_percentage": 9,
      "prolonged_illness_percentage": 20,
      "high_level_of_education_percentage": 42
    }
  },
  {
    "neighbourhood": "Grasrijk",
    "district": "Strijp",
    "2020": {
      "personal_income": 46600,
      "residents": 5845,
      "unhappy_percentage": 2,
      "prolonged_illness_percentage": 14,
      "high_level_of_education_percentage": 48.8
    }
  },
  {
    "neighbourhood": "Hagenkamp",
    "district": "Gestel",
    "2020": {
      "personal_income": 29100,
      "residents": 1183,
      "unhappy_percentage": 3,
      "prolonged_illness_percentage": 18,
      "high_level_of_education_percentage": 32.9
    }
  },
  {
    "neighbourhood": "Hanevoet",
    "district": "Gestel",
    "2020": {
      "personal_income": 31400,
      "residents": 3688,
      "unhappy_percentage": 3,
      "prolonged_illness_percentage": 23,
      "high_level_of_education_percentage": 39.7
    }
  },
  {
    "neighbourhood": "Heesterakker",
    "district": "Woensel-Noord",
    "2020": {
      "personal_income": 37700,
      "residents": 2678,
      "unhappy_percentage": 5,
      "prolonged_illness_percentage": 22,
      "high_level_of_education_percentage": 50.5
    }
  },
  {
    "neighbourhood": "Hemelrijken",
    "district": "Woensel-Zuid",
    "2020": {
      "personal_income": 25400,
      "residents": 3870,
      "unhappy_percentage": 9,
      "prolonged_illness_percentage": 20,
      "high_level_of_education_percentage": 30.8
    }
  },
  {
    "neighbourhood": "Het Ven",
    "district": "Woensel-Zuid",
    "2020": {
      "personal_income": 29500,
      "residents": 3932,
      "unhappy_percentage": 6,
      "prolonged_illness_percentage": 17,
      "high_level_of_education_percentage": 34
    }
  },
  {
    "neighbourhood": "Irisbuurt",
    "district": "Stratum",
    "2020": {
      "personal_income": 39000,
      "residents": 2345,
      "unhappy_percentage": 5,
      "prolonged_illness_percentage": 19,
      "high_level_of_education_percentage": 60.6
    }
  },
  {
    "neighbourhood": "Jagershoef",
    "district": "Woensel-Noord",
    "2020": {
      "personal_income": 25600,
      "residents": 3527,
      "unhappy_percentage": 8,
      "prolonged_illness_percentage": 36,
      "high_level_of_education_percentage": 23.5
    }
  },
  {
    "neighbourhood": "Joriskwartier",
    "district": "Stratum",
    "2020": {
      "personal_income": 35200,
      "residents": 1298,
      "unhappy_percentage": 4,
      "prolonged_illness_percentage": 12,
      "high_level_of_education_percentage": 43.9
    }
  },
  {
    "neighbourhood": "Karpen",
    "district": "Tongelre",
    "2020": {
      "personal_income": 90700,
      "residents": 455,
      "unhappy_percentage": 2,
      "prolonged_illness_percentage": 13,
      "high_level_of_education_percentage": 75
    }
  },
  {
    "neighbourhood": "Kerkdorp Acht",
    "district": "Woensel-Noord",
    "2020": {
      "personal_income": 43000,
      "residents": 3547,
      "unhappy_percentage": 3,
      "prolonged_illness_percentage": 20,
      "high_level_of_education_percentage": 38
    }
  },
  {
    "neighbourhood": "Kerstroosplein",
    "district": "Stratum",
    "2020": {
      "personal_income": 28400,
      "residents": 1829,
      "unhappy_percentage": 8,
      "prolonged_illness_percentage": 18,
      "high_level_of_education_percentage": 34.4
    }
  },
  {
    "neighbourhood": "Koudenhoven",
    "district": "Tongelre",
    "2020": {
      "personal_income": 80900,
      "residents": 516,
      "unhappy_percentage": 2,
      "prolonged_illness_percentage": 13,
      "high_level_of_education_percentage": 66.7
    }
  },
  {
    "neighbourhood": "Kronehoef",
    "district": "Woensel-Zuid",
    "2020": {
      "personal_income": 29700,
      "residents": 4182,
      "unhappy_percentage": 6,
      "prolonged_illness_percentage": 20,
      "high_level_of_education_percentage": 35.5
    }
  },
  {
    "neighbourhood": "Kruidenbuurt",
    "district": "Stratum",
    "2020": {
      "personal_income": 32800,
      "residents": 3067,
      "unhappy_percentage": 6,
      "prolonged_illness_percentage": 21,
      "high_level_of_education_percentage": 41.8
    }
  },
  {
    "neighbourhood": "Lakerlopen",
    "district": "Tongelre",
    "2020": {
      "personal_income": 30100,
      "residents": 3300,
      "unhappy_percentage": 8,
      "prolonged_illness_percentage": 21,
      "high_level_of_education_percentage": 32.6
    }
  },
  {
    "neighbourhood": "Lievendaal",
    "district": "Strijp",
    "2020": {
      "personal_income": 30600,
      "residents": 3157,
      "unhappy_percentage": 6,
      "prolonged_illness_percentage": 22,
      "high_level_of_education_percentage": 19.4
    }
  },
  {
    "neighbourhood": "Limbeek-Noord",
    "district": "Woensel-Zuid",
    "2020": {
      "personal_income": 27700,
      "residents": 2463,
      "unhappy_percentage": 11,
      "prolonged_illness_percentage": 18,
      "high_level_of_education_percentage": 43.6
    }
  },
  {
    "neighbourhood": "Limbeek-Zuid",
    "district": "Woensel-Zuid",
    "2020": {
      "personal_income": 28600,
      "residents": 1405,
      "unhappy_percentage": 11,
      "prolonged_illness_percentage": 18,
      "high_level_of_education_percentage": 34.2
    }
  },
  {
    "neighbourhood": "Looiakkers",
    "district": "Stratum",
    "2020": {
      "personal_income": 37100,
      "residents": 571,
      "unhappy_percentage": 4,
      "prolonged_illness_percentage": 12,
      "high_level_of_education_percentage": 61
    }
  },
  {
    "neighbourhood": "Luytelaer",
    "district": "Woensel-Noord",
    "2020": {
      "personal_income": 53400,
      "residents": 942,
      "unhappy_percentage": 3,
      "prolonged_illness_percentage": 22,
      "high_level_of_education_percentage": 69.8
    }
  },
  {
    "neighbourhood": "Meerrijk",
    "district": "Strijp",
    "2020": {
      "personal_income": 46500,
      "residents": 670,
      "unhappy_percentage": 4,
      "prolonged_illness_percentage": 14,
      "high_level_of_education_percentage": 56.9
    }
  },
  {
    "neighbourhood": "Mensfort",
    "district": "Woensel-Zuid",
    "2020": {
      "personal_income": 28200,
      "residents": 3096,
      "unhappy_percentage": 6,
      "prolonged_illness_percentage": 24,
      "high_level_of_education_percentage": 25.3
    }
  },
  {
    "neighbourhood": "Muschberg, Geestenberg",
    "district": "Tongelre",
    "2020": {
      "personal_income": 28600,
      "residents": 3995,
      "unhappy_percentage": 6,
      "prolonged_illness_percentage": 22,
      "high_level_of_education_percentage": 28.7
    }
  },
  {
    "neighbourhood": "Nieuwe Erven",
    "district": "Stratum",
    "2020": {
      "personal_income": 27600,
      "residents": 1099,
      "unhappy_percentage": 5,
      "prolonged_illness_percentage": 19,
      "high_level_of_education_percentage": 30.8
    }
  },
  {
    "neighbourhood": "Ooievaarsnest",
    "district": "Gestel",
    "2020": {
      "personal_income": 49800,
      "residents": 893,
      "unhappy_percentage": 3,
      "prolonged_illness_percentage": 23,
      "high_level_of_education_percentage": 64.6
    }
  },
  {
    "neighbourhood": "Oude Gracht-Oost",
    "district": "Woensel-Zuid",
    "2020": {
      "personal_income": 46400,
      "residents": 1336,
      "unhappy_percentage": 4,
      "prolonged_illness_percentage": 25,
      "high_level_of_education_percentage": 60.6
    }
  },
  {
    "neighbourhood": "Oude Gracht-West",
    "district": "Woensel-Zuid",
    "2020": {
      "personal_income": 30700,
      "residents": 2860,
      "unhappy_percentage": 4,
      "prolonged_illness_percentage": 25,
      "high_level_of_education_percentage": 38
    }
  },
  {
    "neighbourhood": "Oude Spoorbaan",
    "district": "Gestel",
    "2020": {
      "personal_income": 35100,
      "residents": 2088,
      "unhappy_percentage": 3,
      "prolonged_illness_percentage": 18,
      "high_level_of_education_percentage": 49.7
    }
  },
  {
    "neighbourhood": "Oude Toren",
    "district": "Woensel-Zuid",
    "2020": {
      "personal_income": 28900,
      "residents": 1628,
      "unhappy_percentage": 7,
      "prolonged_illness_percentage": 13,
      "high_level_of_education_percentage": 33.6
    }
  },
  {
    "neighbourhood": "Philipsdorp",
    "district": "Strijp",
    "2020": {
      "personal_income": 38000,
      "residents": 3099,
      "unhappy_percentage": 5,
      "prolonged_illness_percentage": 16,
      "high_level_of_education_percentage": 48.3
    }
  },
  {
    "neighbourhood": "Prinsejagt",
    "district": "Woensel-Noord",
    "2020": {
      "personal_income": 30100,
      "residents": 4742,
      "unhappy_percentage": 8,
      "prolonged_illness_percentage": 24,
      "high_level_of_education_percentage": 28.6
    }
  },
  {
    "neighbourhood": "Puttense Dreef",
    "district": "Stratum",
    "2020": {
      "personal_income": 51000,
      "residents": 1246,
      "unhappy_percentage": 2,
      "prolonged_illness_percentage": 16,
      "high_level_of_education_percentage": 62.2
    }
  },
  {
    "neighbourhood": "Rapelenburg",
    "district": "Gestel",
    "2020": {
      "personal_income": 36500,
      "residents": 1133,
      "unhappy_percentage": 7,
      "prolonged_illness_percentage": 25,
      "high_level_of_education_percentage": 56.3
    }
  },
  {
    "neighbourhood": "Rapenland",
    "district": "Woensel-Zuid",
    "2020": {
      "personal_income": 27700,
      "residents": 2371,
      "unhappy_percentage": 6,
      "prolonged_illness_percentage": 24,
      "high_level_of_education_percentage": 31.1
    }
  },
  {
    "neighbourhood": "Rochusbuurt",
    "district": "Stratum",
    "2020": {
      "personal_income": 34700,
      "residents": 1778,
      "unhappy_percentage": 4,
      "prolonged_illness_percentage": 12,
      "high_level_of_education_percentage": 59.9
    }
  },
  {
    "neighbourhood": "Roosten",
    "district": "Stratum",
    "2020": {
      "personal_income": 60400,
      "residents": 726,
      "unhappy_percentage": 3,
      "prolonged_illness_percentage": 14,
      "high_level_of_education_percentage": 0
    }
  },
  {
    "neighbourhood": "Schoot",
    "district": "Strijp",
    "2020": {
      "personal_income": 31500,
      "residents": 3247,
      "unhappy_percentage": 6,
      "prolonged_illness_percentage": 17,
      "high_level_of_education_percentage": 50.5
    }
  },
  {
    "neighbourhood": "Schouwbroek",
    "district": "Strijp",
    "2020": {
      "personal_income": 32600,
      "residents": 1532,
      "unhappy_percentage": 5,
      "prolonged_illness_percentage": 16,
      "high_level_of_education_percentage": 38.7
    }
  },
  {
    "neighbourhood": "Schrijversbuurt",
    "district": "Gestel",
    "2020": {
      "personal_income": 41600,
      "residents": 3584,
      "unhappy_percentage": 3,
      "prolonged_illness_percentage": 18,
      "high_level_of_education_percentage": 53.7
    }
  },
  {
    "neighbourhood": "Schuttersbosch",
    "district": "Stratum",
    "2020": {
      "personal_income": 46800,
      "residents": 618,
      "unhappy_percentage": 2,
      "prolonged_illness_percentage": 16,
      "high_level_of_education_percentage": 59.5
    }
  },
  {
    "neighbourhood": "Sintenbuurt",
    "district": "Stratum",
    "2020": {
      "personal_income": 34600,
      "residents": 1830,
      "unhappy_percentage": 8,
      "prolonged_illness_percentage": 25,
      "high_level_of_education_percentage": 40.9
    }
  },
  {
    "neighbourhood": "Strijp S",
    "district": "Strijp",
    "2020": {
      "personal_income": 39900,
      "residents": 1665,
      "unhappy_percentage": 5,
      "prolonged_illness_percentage": 13,
      "high_level_of_education_percentage": 66.1
    }
  },
  {
    "neighbourhood": "'t Hofke",
    "district": "Tongelre",
    "2020": {
      "personal_income": 29300,
      "residents": 3683,
      "unhappy_percentage": 6,
      "prolonged_illness_percentage": 22,
      "high_level_of_education_percentage": 36.4
    }
  },
  {
    "neighbourhood": "'t Hool",
    "district": "Woensel-Noord",
    "2020": {
      "personal_income": 29800,
      "residents": 2256,
      "unhappy_percentage": 10,
      "prolonged_illness_percentage": 19,
      "high_level_of_education_percentage": 33.5
    }
  },
  {
    "neighbourhood": "Tempel",
    "district": "Woensel-Noord",
    "2020": {
      "personal_income": 29200,
      "residents": 5079,
      "unhappy_percentage": 4,
      "prolonged_illness_percentage": 26,
      "high_level_of_education_percentage": 24
    }
  },
  {
    "neighbourhood": "Tivoli",
    "district": "Stratum",
    "2020": {
      "personal_income": 23800,
      "residents": 1450,
      "unhappy_percentage": 8,
      "prolonged_illness_percentage": 25,
      "high_level_of_education_percentage": 14.8
    }
  },
  {
    "neighbourhood": "Tongelresche Akkers",
    "district": "Tongelre",
    "2020": {
      "personal_income": 44500,
      "residents": 1453,
      "unhappy_percentage": 8,
      "prolonged_illness_percentage": 22,
      "high_level_of_education_percentage": 50
    }
  },
  {
    "neighbourhood": "Tuindorp",
    "district": "Stratum",
    "2020": {
      "personal_income": 40100,
      "residents": 2952,
      "unhappy_percentage": 5,
      "prolonged_illness_percentage": 19,
      "high_level_of_education_percentage": 63.4
    }
  },
  {
    "neighbourhood": "Vaartbroek",
    "district": "Woensel-Noord",
    "2020": {
      "personal_income": 27900,
      "residents": 5242,
      "unhappy_percentage": 9,
      "prolonged_illness_percentage": 26,
      "high_level_of_education_percentage": 24.9
    }
  },
  {
    "neighbourhood": "Villapark",
    "district": "Tongelre",
    "2020": {
      "personal_income": 57900,
      "residents": 2261,
      "unhappy_percentage": 2,
      "prolonged_illness_percentage": 13,
      "high_level_of_education_percentage": 61.2
    }
  },
  {
    "neighbourhood": "Vlokhoven",
    "district": "Woensel-Noord",
    "2020": {
      "personal_income": 26100,
      "residents": 3538,
      "unhappy_percentage": 10,
      "prolonged_illness_percentage": 29,
      "high_level_of_education_percentage": 27
    }
  },
  {
    "neighbourhood": "Waterrijk",
    "district": "Strijp",
    "2020": {
      "personal_income": 53500,
      "residents": 2228,
      "unhappy_percentage": 4,
      "prolonged_illness_percentage": 14,
      "high_level_of_education_percentage": 63.1
    }
  },
  {
    "neighbourhood": "Winkelcentrum",
    "district": "Woensel-Noord",
    "2020": {
      "personal_income": 39300,
      "residents": 2261,
      "unhappy_percentage": 10,
      "prolonged_illness_percentage": 19,
      "high_level_of_education_percentage": 43.9
    }
  },
  {
    "neighbourhood": "Witte Dame",
    "district": "Centrum",
    "2020": {
      "personal_income": 47400,
      "residents": 2162,
      "unhappy_percentage": 6,
      "prolonged_illness_percentage": 15,
      "high_level_of_education_percentage": 78.5
    }
  },
  {
    "neighbourhood": "Woenselse Heide",
    "district": "Woensel-Noord",
    "2020": {
      "personal_income": 29100,
      "residents": 5252,
      "unhappy_percentage": 6,
      "prolonged_illness_percentage": 32,
      "high_level_of_education_percentage": 28.1
    }
  },
  {
    "neighbourhood": "Woenselse Watermolen",
    "district": "Woensel-Zuid",
    "2020": {
      "personal_income": 44900,
      "residents": 1362,
      "unhappy_percentage": 7,
      "prolonged_illness_percentage": 13,
      "high_level_of_education_percentage": 80.1
    }
  },
  {
    "neighbourhood": "Woensel-West",
    "district": "Woensel-Zuid",
    "2020": {
      "personal_income": 27200,
      "residents": 3878,
      "unhappy_percentage": 8,
      "prolonged_illness_percentage": 19,
      "high_level_of_education_percentage": 41.3
    }
  },
  {
    "neighbourhood": "Zandrijk",
    "district": "Strijp",
    "2020": {
      "personal_income": 41200,
      "residents": 2940,
      "unhappy_percentage": 2,
      "prolonged_illness_percentage": 14,
      "high_level_of_education_percentage": 42.1
    }
  },
  {
    "neighbourhood": "Zwaanstraat",
    "district": "Strijp",
    "2020": {
      "personal_income": 59100,
      "residents": 902,
      "unhappy_percentage": 3,
      "prolonged_illness_percentage": 16,
      "high_level_of_education_percentage": 81.4
    }
  }
]
